mindone/__init__.py
mindone/version.py
mindone/comfyui/execution.py
mindone/comfyui/latent_preview.py
mindone/comfyui/main.py
mindone/comfyui/node_helpers.py
mindone/comfyui/nodes.py
mindone/comfyui/server.py
mindone/comfyui/comfy/cli_args.py
mindone/comfyui/comfy/clip_model.py
mindone/comfyui/comfy/text_encoders/bert.py
mindone/comfyui/comfy/text_encoders/flux.py
mindone/comfyui/comfy/text_encoders/hunyuan_video.py
mindone/comfyui/comfy/text_encoders/llama.py
mindone/comfyui/comfy/text_encoders/qwen_image.py
mindone/comfyui/comfy/text_encoders/qwen_vl.py
mindone/comfyui/comfy/text_encoders/sd3_clip.py
mindone/comfyui/comfy/text_encoders/t5.py
mindone/data/__init__.py
mindone/data/data_split.py
mindone/data/dataset.py
mindone/data/loader.py
mindone/data/video_reader.py
mindone/diffusers/README.md
mindone/diffusers/SUPPORT_LIST.md
mindone/diffusers/__init__.py
mindone/diffusers/callbacks.py
mindone/diffusers/configuration_utils.py
mindone/diffusers/image_processor.py
mindone/diffusers/optimization.py
mindone/diffusers/training_utils.py
mindone/diffusers/video_processor.py
mindone/diffusers/guiders/__init__.py
mindone/diffusers/guiders/adaptive_projected_guidance.py
mindone/diffusers/guiders/auto_guidance.py
mindone/diffusers/guiders/classifier_free_guidance.py
mindone/diffusers/guiders/classifier_free_zero_star_guidance.py
mindone/diffusers/guiders/frequency_decoupled_guidance.py
mindone/diffusers/guiders/guider_utils.py
mindone/diffusers/guiders/perturbed_attention_guidance.py
mindone/diffusers/guiders/skip_layer_guidance.py
mindone/diffusers/guiders/smoothed_energy_guidance.py
mindone/diffusers/guiders/tangential_classifier_free_guidance.py
mindone/diffusers/hooks/__init__.py
mindone/diffusers/hooks/_common.py
mindone/diffusers/hooks/_helpers.py
mindone/diffusers/hooks/context_parallel.py
mindone/diffusers/hooks/faster_cache.py
mindone/diffusers/hooks/first_block_cache.py
mindone/diffusers/hooks/hooks.py
mindone/diffusers/hooks/layer_skip.py
mindone-0.5.0.dist-info/METADATA
mindone-0.5.0.dist-info/WHEEL
mindone-0.5.0.dist-info/licenses/LICENSE
mindone-0.5.0.dist-info/RECORD
