Metadata-Version: 2.4
Name: mindone
Version: 0.5.0
Summary: ONE for all, Optimal generator with No Exception.
Project-URL: Homepage, https://pypi.org/project/mindone/
Project-URL: Documentation, https://mindspore-lab.github.io/mindone/
Project-URL: Issues, https://github.com/mindspore-lab/mindone/issues
Project-URL: Source, https://github.com/mindspore-lab/mindone
Author-email: MindSpore Lab <mindspore-lab@example.com>
License-Expression: Apache-2.0
License-File: LICENSE
Keywords: artificial intelligence,deep learning,diffusion,generative model,mindspore
Classifier: Development Status :: 4 - Beta
Classifier: Intended Audience :: Developers
Classifier: Intended Audience :: Education
Classifier: Intended Audience :: Science/Research
Classifier: License :: OSI Approved :: Apache Software License
Classifier: Operating System :: OS Independent
Classifier: Programming Language :: Python :: 3 :: Only
Classifier: Programming Language :: Python :: 3.9
Classifier: Topic :: Scientific/Engineering :: Artificial Intelligence
Requires-Python: >=3.9
Requires-Dist: better-profanity
Requires-Dist: huggingface-hub>=0.20.2
Requires-Dist: mindcv==0.3.0
Requires-Dist: nltk
Requires-Dist: numpy<2.0
Requires-Dist: omegaconf
Requires-Dist: opencv-python
Requires-Dist: pyyaml
Requires-Dist: safetensors>=0.3.1
Requires-Dist: sentencepiece
Requires-Dist: tqdm
Requires-Dist: trampoline
Requires-Dist: transformers==4.57.1
Provides-Extra: dev
Requires-Dist: datasets; extra == 'dev'
Requires-Dist: ftfy; extra == 'dev'
Requires-Dist: jinja2; extra == 'dev'
Requires-Dist: mike>=2.1; extra == 'dev'
Requires-Dist: mkdocs-git-authors-plugin>=0.9; extra == 'dev'
Requires-Dist: mkdocs-git-revision-date-localized-plugin>=1.2; extra == 'dev'
Requires-Dist: mkdocs-material>=9.5; extra == 'dev'
Requires-Dist: mkdocs-static-i18n>=1.2; extra == 'dev'
Requires-Dist: mkdocs>=1.6; extra == 'dev'
Requires-Dist: mkdocstrings[python]>=0.25; extra == 'dev'
Requires-Dist: parameterized; extra == 'dev'
Requires-Dist: pre-commit; extra == 'dev'
Requires-Dist: protobuf; extra == 'dev'
Requires-Dist: pytest; extra == 'dev'
Requires-Dist: pytest-cov; extra == 'dev'
Requires-Dist: pytest-mock; extra == 'dev'
Requires-Dist: tensorboard; extra == 'dev'
Requires-Dist: tensorboardx; extra == 'dev'
Provides-Extra: docs
Requires-Dist: mike>=2.1; extra == 'docs'
Requires-Dist: mkdocs-git-authors-plugin>=0.9; extra == 'docs'
Requires-Dist: mkdocs-git-revision-date-localized-plugin>=1.2; extra == 'docs'
Requires-Dist: mkdocs-material>=9.5; extra == 'docs'
Requires-Dist: mkdocs-static-i18n>=1.2; extra == 'docs'
Requires-Dist: mkdocs>=1.6; extra == 'docs'
Requires-Dist: mkdocstrings[python]>=0.25; extra == 'docs'
Provides-Extra: lint
Requires-Dist: pre-commit; extra == 'lint'
Provides-Extra: tests
Requires-Dist: parameterized; extra == 'tests'
Requires-Dist: pytest; extra == 'tests'
Requires-Dist: pytest-cov; extra == 'tests'
Requires-Dist: pytest-mock; extra == 'tests'
Provides-Extra: training
Requires-Dist: datasets; extra == 'training'
Requires-Dist: ftfy; extra == 'training'
Requires-Dist: jinja2; extra == 'training'
Requires-Dist: protobuf; extra == 'training'
Requires-Dist: tensorboard; extra == 'training'
Requires-Dist: tensorboardx; extra == 'training'
